pyfetcher/__init__.py
pyfetcher-1.7.5.dist-info/METADATA
pyfetcher-1.7.5.dist-info/WHEEL
pyfetcher-1.7.5.dist-info/licenses/LICENSE
pyfetcher-1.7.5.dist-info/RECORD
